finetune/__init__.py
finetune/alpaca_shuffler.py
finetune/main.py
finetune/GRPO/ModGRPOTrainer.py
finetune/GRPO/__init__.py
finetune/GRPO/export.py
finetune/GRPO/hive_reward_parser.py
finetune/GRPO/hivetrainer.py
finetune/GRPO/rewards/__init__.py
finetune/GRPO/rewards/format_rewards.py
finetune/GRPO/rewards/hive_rewards/__init__.py
finetune/GRPO/rewards/hive_rewards/hive_reward_datasets.py
finetune/GRPO/rewards/hive_rewards/hive_rewards.py
finetune/GRPO/test/__init__.py
finetune/GRPO/test/test_extrat.py
finetune/GRPO/test/test_reward-json_parse.py
finetune/converter/__init__.py
finetune/converter/csv_to_parquet.py
finetune/filter/BERT_filter.py
finetune/filter/__init__.py
finetune/filter/text_dataset.py
finetune/parquet/__init__.py
finetune/parquet/agentManager.py
finetune/parquet/config.py
finetune/parquet/llm_init.py
finetune/parquet/read_parquet.py
finetune/parquet/fine_tuning/__init__.py
finetune/parquet/fine_tuning/tools.py
finetune/parquet/schemas/__init__.py
finetune/parquet/schemas/schemas.py
finetune/parquet/schemas/works/PydanticSafetyParser.py
finetune/parquet/schemas/works/__init__.py
finetune/structure/__init__.py
finetune/structure/alpaca.py
finetune/test/__init__.py
finetune/test/test.py
finetune/test/test_api_price.py
finetune/test/test_api_speed.py
finetune/test/functions/__init__.py
finetune/test/functions/shrink_op.py
finetune/tools/__init__.py
finetune/tools/check/__init__.py
finetune/tools/check/checking.py
finetune/tools/cidr/__init__.py
finetune/tools/cidr/cidr2iplist.py
finetune/tools/dataset_convert/__init__.py
finetune/tools/dataset_convert/agentManager.py
finetune/tools/dataset_convert/config.py
finetune/tools/dataset_convert/llm_init.py
finetune/tools/dataset_convert/main.py
finetune/tools/dataset_convert/schemas/__init__.py
finetune/tools/dataset_convert/schemas/schemas.py
finetune/tools/dataset_convert/schemas/works/PydanticSafetyParser.py
finetune/tools/dataset_convert/schemas/works/__init__.py
finetune/tools/dingtalk/__init__.py
finetune_cli-0.8.0.dist-info/METADATA
finetune_cli-0.8.0.dist-info/WHEEL
finetune_cli-0.8.0.dist-info/entry_points.txt
finetune_cli-0.8.0.dist-info/top_level.txt
finetune_cli-0.8.0.dist-info/RECORD
