Metadata-Version: 2.4
Name: finetune-cli
Version: 0.8.0
Summary: 一个将原始语料库变成微调需要的alpaca数据集格式的工具
Author: stupidfish001
Author-email: shovel@hscsec.cn
Classifier: Programming Language :: Python :: 3
Classifier: License :: OSI Approved :: MIT License
Classifier: Operating System :: OS Independent
Requires-Python: >=3.6
Requires-Dist: langchain
Requires-Dist: typer
Requires-Dist: pandas
Requires-Dist: loguru
Requires-Dist: kink
Requires-Dist: langchain_openai
Requires-Dist: fastparquet
Requires-Dist: pyarrow
Requires-Dist: transformers
Requires-Dist: trl
Requires-Dist: peft
Requires-Dist: bitsandbytes
Requires-Dist: tensorboard
Dynamic: author
Dynamic: author-email
Dynamic: classifier
Dynamic: requires-dist
Dynamic: requires-python
Dynamic: summary
